[
    {
      "pool_pda": "5CpB1iVbxnW5d5XpsBRt6jUD5ffac1GjSZm6eF4GHVif",
      "merkle_root_upload_authority": "DJ9MAJHQ3YjPfUFN7b3LguSFmFP8pUkxKYDkVBNUFnK4",
      "merkle_root": [
        0, 0, 0, 0, 0, 0, 0, 0,
        0, 0, 0, 0, 0, 0, 0, 0,
        0, 0, 0, 0, 0, 0, 0, 0,
        0, 0, 0, 0, 0, 0, 0, 0
      ],
      "tree_nodes": [
        {
          "predictor": "2btmKgkE8ZVb8f5F8J1v7H8d9L6P3T2K1r3u7S5e9XwY",
          "prize_amount": 100,
          "proof": null
        },
        {
          "predictor": "6vYk9QpZ8LdFrM2NaB7m3o9W1qP8U3jR4T5p6b8Y2ZxW",
          "prize_amount": 200,
          "proof": null
        }
      ],
      "max_num_nodes": 2
    }
  ]